solargis/__init__.py
solargis/documentation_mcp_server/__init__.py
solargis/documentation_mcp_server/models.py
solargis/documentation_mcp_server/server.py
solargis/documentation_mcp_server/server_utils.py
solargis/documentation_mcp_server/utils.py
solargis_documentation_mcp_server-0.1.0.dist-info/METADATA
solargis_documentation_mcp_server-0.1.0.dist-info/WHEEL
solargis_documentation_mcp_server-0.1.0.dist-info/entry_points.txt
solargis_documentation_mcp_server-0.1.0.dist-info/RECORD
