Metadata-Version: 2.4
Name: solargis.documentation-mcp-server
Version: 0.1.0
Summary: Model Context Protocol (MCP) server for Solargis documentation
Project-URL: Homepage, https://solargis.github.io/mcp/
Project-URL: Documentation, https://solargis.github.io/mcp/servers/documentation-mcp-server/
Project-URL: Source, https://github.com/solargis/mcp.git
Project-URL: Bug Tracker, https://github.com/solargis/mcp/issues
Author: Solargis
License: Apache-2.0
Keywords: documentation,mcp,model-context-protocol,solargis
Classifier: License :: OSI Approved :: Apache Software License
Classifier: Operating System :: OS Independent
Classifier: Programming Language :: Python
Classifier: Programming Language :: Python :: 3
Classifier: Programming Language :: Python :: 3.11
Classifier: Programming Language :: Python :: 3.12
Classifier: Programming Language :: Python :: 3.13
Requires-Python: >=3.11
Requires-Dist: beautifulsoup4>=4.13.5
Requires-Dist: httpx>=0.28.1
Requires-Dist: loguru>=0.7.3
Requires-Dist: markdownify>=1.2.0
Requires-Dist: mcp[cli]>=1.13.1
Requires-Dist: pydantic>=2.11.7
